<?xml version="1.0" encoding="utf-8" ?>
<LanguageData>

  <Overview>Visão geral</Overview>
  <OverviewTip>Gerenciar prioridades de trabalho da colônia e estatísticas.</OverviewTip>
  <ResearchTip>Analisar e decidir sobre projetos de pesquisa.</ResearchTip>
  <Wiki>Wiki</Wiki>
  <WikiTip>Abre o navegador da Web para ver o RimWorld wiki e obter ajuda do jogo.</WikiTip>
  <Menu>Menu</Menu>
  <MenuTip>Salvar, carregar, ou sair do jogo, ou mudar as opções.</MenuTip>

  <Architect>Arquiteto</Architect>


</LanguageData>