<?xml version="1.0" encoding="utf-8" ?>
<LanguageData>

	<WorkTagNone>Nenhum</WorkTagNone>
	<WorkTagIntellectual>Intelectual</WorkTagIntellectual>
	<WorkTagManualDumb>Estúpido</WorkTagManualDumb>
	<WorkTagManualSkilled>Habilidoso</WorkTagManualSkilled>
	<WorkTagViolent>Brutal</WorkTagViolent>
	<WorkTagCaring>Portetor</WorkTagCaring>
	<WorkTagSocial>Social</WorkTagSocial>
	<WorkTagScary>Assustado</WorkTagScary>
	<WorkTagArtistic>Artístico</WorkTagArtistic>
	<WorkTagCrafting>Artesanato</WorkTagCrafting>
	<WorkTagCooking>Cozinhando</WorkTagCooking>
	<WorkTagFirefighting>Bombeiro</WorkTagFirefighting>
	<WorkTagCleaning>Limpando</WorkTagCleaning>
	<WorkTagHauling>Carregando</WorkTagHauling>
	<WorkTagPlantWork>Plantando</WorkTagPlantWork>
	<WorkTagMining>Minerando</WorkTagMining>

  
  
  
</LanguageData>